elasticedge/__init__.py
elasticedge/api/__init__.py
elasticedge/api/deploy.py
elasticedge/api/exceptions.py
elasticedge/api/graphql.py
elasticedge/api/healthcheck.py
elasticedge/auth/__init__.py
elasticedge/console/__init__.py
elasticedge/console/application.py
elasticedge/console/commands/__init__.py
elasticedge/console/commands/deploy.py
elasticedge/console/commands/login.py
elasticedge-0.5.0.dist-info/entry_points.txt
elasticedge-0.5.0.dist-info/WHEEL
elasticedge-0.5.0.dist-info/METADATA
elasticedge-0.5.0.dist-info/RECORD
