Metadata-Version: 2.1
Name: elasticedge
Version: 0.5.0
Summary: 
Author: Marco Acierno
Author-email: marcoaciernoemail@gmail.com
Requires-Python: >=3.6,<4.0
Classifier: Programming Language :: Python :: 3
Classifier: Programming Language :: Python :: 3.6
Classifier: Programming Language :: Python :: 3.7
Classifier: Programming Language :: Python :: 3.8
Requires-Dist: cleo (>=0.7.6,<0.8.0)
Requires-Dist: pyyaml (>=5.2,<6.0)
Requires-Dist: requests (>=2.22.0,<3.0.0)
